linlangleyprimecosmos-0.5.dist-info/licenses/LICENSE
primepackage/__init__.py
primepackage/generator.py
primepackage/primeio.py
primepackage/primemodule.py
linlangleyprimecosmos-0.5.dist-info/METADATA
linlangleyprimecosmos-0.5.dist-info/WHEEL
linlangleyprimecosmos-0.5.dist-info/entry_points.txt
linlangleyprimecosmos-0.5.dist-info/top_level.txt
linlangleyprimecosmos-0.5.dist-info/RECORD
