Metadata-Version: 2.4
Name: linlangleyprimecosmos
Version: 0.5
Summary: Demo for building a Python project
Home-page: http://lin-chen-langley.github.io
Author: Lin Chen
Author-email: lin.chen@ieee.org
License: Creative Commons Attribution-Noncommercial-Share Alike license
Project-URL: PyPI, https://pypi.org/manage/project/linlangleyprime/releases/
Project-URL: Conda, https://anaconda.org/linchenVA/linlangleyprime
Classifier: Development Status :: 4 - Beta
Classifier: Environment :: X11 Applications :: GTK
Classifier: Intended Audience :: End Users/Desktop
Classifier: Intended Audience :: Developers
Classifier: License :: OSI Approved :: GNU General Public License (GPL)
Classifier: Operating System :: POSIX :: Linux
Classifier: Programming Language :: Python
Classifier: Topic :: Desktop Environment
Classifier: Topic :: Text Processing :: Fonts
Requires-Python: >=3.9
License-File: LICENSE
Requires-Dist: dash
Provides-Extra: test
Requires-Dist: pytest; extra == "test"
Requires-Dist: pytest-cov; extra == "test"
Provides-Extra: build
Requires-Dist: build; extra == "build"
Provides-Extra: publish
Requires-Dist: twine; extra == "publish"
Dynamic: author
Dynamic: author-email
Dynamic: classifier
Dynamic: description
Dynamic: description-content-type
Dynamic: home-page
Dynamic: license
Dynamic: license-file
Dynamic: project-url
Dynamic: provides-extra
Dynamic: requires-dist
Dynamic: requires-python
Dynamic: summary
